{"type":"HOSTEL","name":"Little Drifter Surry Hills","nameEN":"Little Drifter Surry Hills","isActive":true,"isNew":false,"description":"Welcome to Little Drifter Surry Hills.\r\n\r\nRight in the heart of Sydney’s most creative and eclectic neighborhood, Little Drifter Surry Hills is your perfect base for an unforgettable stay. Picture a place where mornings begin with new friendships and evenings unfold into unexpected adventures-that’s what we’re all about.\r\n\r\nJust a short walk from Central Station, our high-end neighbourhood hostel offers effortless access to Sydney’s city center, stunning beaches, and iconic harbour. Whether you're here to explore, work, or simply soak up the vibrant local scene, Little Drifter Surry Hills is where your journey starts.\r\n\r\nOur space is designed for comfort and connection. Cook up a storm in our fully-equipped communal kitchen, unwind in the courtyard and alfresco dining areas, or settle into our cosy lounge spaces for a relaxed evening. Whether you're planning your next adventure or just enjoying the moment, there’s always a spot for you here.\r\n\r\nWe can’t wait to welcome you to Little Drifter Surry Hills - a place where new friendships form, stories unfold, and the city is yours to explore. Let's drift away together, somewhere, forever.","hostelworldSays":null,"hostelSays":null,"location":{"address1":"203 Cleveland Street, Surry Hills","address2":"","city":{"id":81,"name":"Sydney","nameEN":"Sydney"},"country":{"id":13,"name":"Australia","nameEN":"Australia"},"region":{"id":77,"name":"New South Wales","nameEN":"New South Wales"},"latitude":"-33.8897210","longitude":"151.2036870","distance":{"kilometers":2.53,"miles":1.57}},"maxGuestsPerBooking":8,"depositPercentage":15,"ratings":{"security":88,"location":83,"staff":74,"atmosphere":62,"clean":69,"facilities":72,"value":74,"overall":75,"ratingsCount":100},"groupInformation":{"listingInfo":"","terms":"","cancellationTerms":"","additionalTerms":"","typesNotAccepted":["JUNIORPRIMARYSCHOOL","HIGHSECONDARYSCHOOL","COLLEGEUNIVERSITY","BUSINESSTRIP","STAGHENBACHELORPARTY","SPORTSGROUP","CULTURALGROUP","HOLIDAYWITHFRIENDS"],"remainderDue":"","ageRangesAccepted":[""],"maxGuestsPerBooking":0},"currency":"AUD","houseRules":{"notes":"As a shared experience we ask all guests to follow certain principles and guidelines.\r\n\r\n- Check-out is 10am, unless a late checkout has been pre-arranged.\r\n- Late checkouts after 12pm will incur a fee equivalent to one night's stay.\r\n- Each guest must remain in their designated bed and speak with a host if they wish to change.\r\n- Visitors are not permitted on guest levels or in guest-only communal areas.\r\n- No sleeping bags are permitted as they can carry unwanted pests.\r\n- No bikes, drugs, smoking or vaping anywhere inside the property.\r\n- No food or drink (besides water) is permitted inside the rooms.\r\n- No large electrical items such as tv's, e-bike batteries, heaters or other fire hazards.\r\n- No sleeping in communal areas - that's what the beds are for.\r\n\r\nGuests who do not follow principles may have their booking cancelled.\r\n\r\n- We hold no responsibility for the loss, theft or damage of your personal belongings.\r\n- Guests must label and date food in kitchens otherwise it will be discarded.\r\n- Guests are required to wash and return items used within the kitchen for other guests.\r\n- Full payment for stays must be made prior to or upon check-in.\r\n- Extensions must be confirmed as your access will be deactivated and belongings removed.\r\n- Staff on-shift may conduct regular room checks.\r\n- To respect neighbours, we ask for no noise outside the premises.\r\n- Certain areas will be closed early to allow rest for both guests and neighbours.\r\n- We reserve the right to evict without refund any individuals who do not comply.\r\n- Non-compliance with eviction instructions will result in the authorities being contacted.\r\n- Guests must be 18+ unless staying in a private room with a legal parent or guardian.\r\n- Each guest must provide valid photo ID and a credit card in their name for incidentals upon check-in.\r\n\r\nLong story short, we love you, but we ask that you share the love around respectfully.","checkin":{"from":14,"until":24},"latestCheckout":"10:00","policies":["TAXESINCLUDED"],"cancellationPolicy":{"canxDays":0,"freeCancellationEnabled":true}},"taxes":[],"hoscars":{"awards":[],"nominations":[]},"facilities":[{"name":"FACILITYCATEGORYFREE","id":1,"facilities":[{"id":90,"name":"FREEWIFI"}]},{"name":"FACILITYCATEGORYSERVICES","id":3,"facilities":[{"id":20,"name":"24HOURRECEPTION"},{"id":121,"name":"HOUSEKEEPING"}]},{"name":"FACILITYCATEGORYENTERTAINMENT","id":5,"facilities":[{"id":4,"name":"INTERNETACCESS"},{"id":95,"name":"BOARDGAMES"},{"id":109,"name":"POOLTABLE"},{"id":133,"name":"WIFI"},{"id":386,"name":"SMARTTV"}]},{"name":"FACILITYCATEGORYFOODANDDRINKS","id":4,"facilities":[{"id":29,"name":"BBQ"},{"id":86,"name":"VENDINGMACHINES"}]},{"name":"FACILITYCATEGORYKITCHEN","id":6,"facilities":[{"id":92,"name":"KITCHEN"},{"id":101,"name":"UTENSILS"},{"id":124,"name":"MICROWAVE"},{"id":360,"name":"POTSANDPANS"},{"id":362,"name":"STOVE"},{"id":363,"name":"TOASTER"}]},{"name":"FACILITYCATEGORYLAUNDRY","id":8,"facilities":[{"id":5,"name":"LAUNDRYFACILITIES"},{"id":102,"name":"DRYER"},{"id":131,"name":"WASHINGMACHINE"},{"id":368,"name":"FREEIRONIRONINGBOARD"}]},{"name":"FACILITYCATEGORYWELLNESS","id":9,"facilities":[{"id":38,"name":"GYM"},{"id":81,"name":"HOTSHOWERS"}]},{"name":"FACILITYCATEGORYOUTDOORS","id":10,"facilities":[{"id":107,"name":"OUTDOORTERRACE"}]},{"name":"FACILITYCATEGORYSAFETYANDSECURITY","id":11,"facilities":[{"id":14,"name":"LOCKERS"},{"id":378,"name":"SMOKEALARMS"},{"id":379,"name":"SMOKEDETECTOR"}]},{"name":"FACILITYCATEGORYSOCIALAREAS","id":12,"facilities":[{"id":24,"name":"COMMONROOM"},{"id":380,"name":"LOUNGEROOM"},{"id":381,"name":"SOCIALBALCONY"}]},{"name":"FACILITYCATEGORYBEDROOM","id":13,"facilities":[{"id":9,"name":"LINENINCLUDED"},{"id":111,"name":"READINGLIGHT"},{"id":382,"name":"CHARGINGPLUGS"}]},{"name":"FACILITYCATEGORYAVAILABLEFORAFEE","id":15,"facilities":[{"id":115,"name":"HAIRDRYERSFORHIRE"},{"id":152,"name":"LATECHECKOUT"}]}],"images":[{"prefix":"a.hwstatic.com/image/upload/f_auto,q_auto","suffix":"/v1/propertyimages/3/328846/b3sx2tk8jnq3u9gyrf5e","position":1},{"prefix":"a.hwstatic.com/image/upload/f_auto,q_auto","suffix":"/v1/propertyimages/3/328846/tyijpr6te5rqauimf3zs","position":2},{"prefix":"a.hwstatic.com/image/upload/f_auto,q_auto","suffix":"/v1/propertyimages/3/328846/mamcfokigla8frlhsyru","position":3},{"prefix":"a.hwstatic.com/image/upload/f_auto,q_auto","suffix":"/v1/propertyimages/3/328846/j6bgwvgtkyjjjjjokfjo","position":4},{"prefix":"a.hwstatic.com/image/upload/f_auto,q_auto","suffix":"/v1/propertyimages/3/328846/nddl93kj4yqwty1ac36v","position":5},{"prefix":"a.hwstatic.com/image/upload/f_auto,q_auto","suffix":"/v1/propertyimages/3/328846/nfdsr1e1udw4ot9lewje","position":6},{"prefix":"a.hwstatic.com/image/upload/f_auto,q_auto","suffix":"/v1/propertyimages/3/328846/seyxhpksb62chfkdcbvo","position":7},{"prefix":"a.hwstatic.com/image/upload/f_auto,q_auto","suffix":"/v1/propertyimages/3/328846/yqngwmbspqo1bsbflzje","position":8},{"prefix":"a.hwstatic.com/image/upload/f_auto,q_auto","suffix":"/v1/propertyimages/3/328846/yktahyebdn0ximnxncfk","position":9},{"prefix":"a.hwstatic.com/image/upload/f_auto,q_auto","suffix":"/v1/propertyimages/3/328846/poesj3zqymcdfbjwfe7a","position":10},{"prefix":"a.hwstatic.com/image/upload/f_auto,q_auto","suffix":"/v1/propertyimages/3/328846/kvc5qorxkjcmvhf6xrlj","position":11},{"prefix":"a.hwstatic.com/image/upload/f_auto,q_auto","suffix":"/v1/propertyimages/3/328846/wshy34nj1amtpe52cczx","position":12},{"prefix":"a.hwstatic.com/image/upload/f_auto,q_auto","suffix":"/v1/propertyimages/3/328846/p8p4laieathmrmojtfra","position":13},{"prefix":"a.hwstatic.com/image/upload/f_auto,q_auto","suffix":"/v1/propertyimages/3/328846/qhp4lcdsgy5picplk3fr","position":14},{"prefix":"a.hwstatic.com/image/upload/f_auto,q_auto","suffix":"/v1/propertyimages/3/328846/xzpibuprah28jtpeh2tn","position":15},{"prefix":"a.hwstatic.com/image/upload/f_auto,q_auto","suffix":"/v1/propertyimages/3/328846/nzwmpa3lrchwvcpcsowq","position":16},{"prefix":"a.hwstatic.com/image/upload/f_auto,q_auto","suffix":"/v1/propertyimages/3/328846/doxkyjz7shv24nudh9hi","position":17},{"prefix":"a.hwstatic.com/image/upload/f_auto,q_auto","suffix":"/v1/propertyimages/3/328846/sagtmymqohyhy0r05pnq","position":18},{"prefix":"a.hwstatic.com/image/upload/f_auto,q_auto","suffix":"/v1/propertyimages/3/328846/gdqpy9okdreieppl5qke","position":19},{"prefix":"a.hwstatic.com/image/upload/f_auto,q_auto","suffix":"/v1/propertyimages/3/328846/zbngnq6k0k5ldep7ohlk","position":20},{"prefix":"a.hwstatic.com/image/upload/f_auto,q_auto","suffix":"/v1/propertyimages/3/328846/c00icepyrerste7mixuv","position":21},{"prefix":"a.hwstatic.com/image/upload/f_auto,q_auto","suffix":"/v1/propertyimages/3/328846/tlcwx3ykpktt7p3t4l2r","position":22},{"prefix":"a.hwstatic.com/image/upload/f_auto,q_auto","suffix":"/v1/propertyimages/3/328846/krf47bdjughvudurrjmh","position":23},{"prefix":"a.hwstatic.com/image/upload/f_auto,q_auto","suffix":"/v1/propertyimages/3/328846/fzmxvfngnbywrs1ndor0","position":24},{"prefix":"a.hwstatic.com/image/upload/f_auto,q_auto","suffix":"/v1/propertyimages/3/328846/pqgi8piq4uqv6isyjrdf","position":25},{"prefix":"a.hwstatic.com/image/upload/f_auto,q_auto","suffix":"/v1/propertyimages/3/328846/pzcxvbl7wwzcwap13j3b","position":26},{"prefix":"a.hwstatic.com/image/upload/f_auto,q_auto","suffix":"/v1/propertyimages/3/328846/gsvznzpijmis2tdhcoec","position":27},{"prefix":"a.hwstatic.com/image/upload/f_auto,q_auto","suffix":"/v1/propertyimages/3/328846/bpbspxn28yitwxc9fb9c","position":28},{"prefix":"a.hwstatic.com/image/upload/f_auto,q_auto","suffix":"/v1/propertyimages/3/328846/gjtkxqnemorawtt9op1r","position":29},{"prefix":"a.hwstatic.com/image/upload/f_auto,q_auto","suffix":"/v1/propertyimages/3/328846/wcqhpdwr74h1f8wj5bu7","position":30}],"videos":[],"video":null,"payments":{"payNow":false},"paymentMethods":["PayPal","AliPay","Visa","Mastercard","VisaDebit","Electron","Maestro","JCB"],"hostelworldRecommends":false,"isElevateProperty":false,"hasExperiences":false,"timesBookedToday":34,"promotions":[{"id":205041,"type":"APPS","stack":true,"name":"App-only deal","created":"2024-10-31T00:24:36","isActive":true,"conditions":{"stayDates":{"isTotalNightsGreaterOrEqualThan":1},"propertyIds":{"containsAnyOf":[328846]},"ratePlanTypes":{"containsAnyStringOf":["NRR","Standard_BB","NRR_BB"]},"roomTypeIds":{"containsAnyOf":[974846,974861]},"channel":{"isOneStringOf":["APPS"]}},"benefits":{"PERCENTDISCOUNT":{"value":10}}},{"id":243275,"type":"CUSTOM","stack":false,"name":"ALLPLATFORMS","created":"2025-10-01T21:38:33","isActive":true,"conditions":{"stayDates":{"isAfterOrSameDayThan":"2025-10-02","isBeforeOrSameDayThan":"2025-11-30","isNotOneDayOf":["2025-10-04"],"isTotalNightsGreaterOrEqualThan":1},"propertyIds":{"containsAnyOf":[328846]},"ratePlanTypes":{"containsAnyStringOf":["NRR","Standard_BB","NRR_BB"]},"roomTypeIds":{"containsAnyOf":[974846,974847,974849,974850,974851,974853,974854,974855,974857,974858,999327,999328,999329,999330,2010371,2010372]}},"benefits":{"PERCENTDISCOUNT":{"value":30}}},{"id":221307,"type":"CUSTOM","stack":false,"name":"Weekly","created":"2025-03-28T03:26:08","isActive":true,"conditions":{"stayDates":{"isNotOneDayOf":["2025-12-31","2026-01-01"],"isTotalNightsGreaterOrEqualThan":7},"propertyIds":{"containsAnyOf":[328846]},"ratePlanTypes":{"containsAnyStringOf":["Standard","NRR","Standard_BB","NRR_BB"]}},"benefits":{"PERCENTDISCOUNT":{"value":12}}},{"id":237912,"type":"CUSTOM","stack":false,"name":"Early Bird","created":"2025-08-15T06:51:09","isActive":true,"conditions":{"stayDates":{"isNotOneDayOf":["2025-12-30","2025-12-31","2026-01-01","2026-01-02"],"isDaysToArrivalMoreOrEqualThan":14,"isTotalNightsGreaterOrEqualThan":2},"propertyIds":{"containsAnyOf":[328846]},"ratePlanTypes":{"containsAnyStringOf":["NRR","Standard_BB","NRR_BB"]}},"benefits":{"PERCENTDISCOUNT":{"value":15}}},{"id":242999,"type":"CUSTOM","stack":false,"name":"Entire Dorm Promo","created":"2025-09-30T03:24:27","isActive":true,"conditions":{"stayDates":{"isAfterOrSameDayThan":"2025-09-30","isBeforeOrSameDayThan":"2025-10-31","isTotalNightsGreaterOrEqualThan":1},"propertyIds":{"containsAnyOf":[328846]},"ratePlanTypes":{"containsAnyStringOf":["NRR","Standard_BB","NRR_BB"]},"roomTypeIds":{"containsAnyOf":[999327,999328,999329,999330,2010372]}},"benefits":{"PERCENTDISCOUNT":{"value":15}}}],"categories":[]}
