{"type":"HOSTEL","name":"Backpackers In Paradise Resort","nameEN":"Backpackers In Paradise Resort","isActive":true,"isNew":false,"description":"Since 1986, Backpackers in Paradise has been creating that iconic 80’s vibe and is one of the first and longest-running hostels on the Gold Coast! Just a 2-minute walk from the city center and the beach, it’s perfectly located to enjoy all the best that Surfers Paradise has to offer, from trendy restaurants and tourist attractions to stunning beaches and lively clubs.\r\n\r\nBackpackers in Paradise is the ideal mix of party and relaxation. Our fully licensed bar is open all day, offering daily happy hours and a variety of drinks, so please note that BYO is not allowed. Our party reps organize exciting nightly activities and offer nightclub passes, ensuring every night is memorable. You’ll also love our on-site café, swimming pool, pool tables, cinema room, table tennis, free Wi-Fi, smoking area, laundry facilities, and a large, shared kitchen with all the essentials.\r\n\r\nWe offer comfortable and spacious dorms that sleep between 4-20 people, all with ensuite bathrooms. For more privacy, we have rooms for up to 2 people. All dorms and private rooms are cleaned daily by our friendly housekeeping team.\r\n\r\nCheck-in is at 2 PM, and checkout is at 10 AM. A $25 security bond is required upon arrival. Dorms are available for guests aged 18-35, and private rooms are for those over 18. All guests must present a valid international passport at check-in—no exceptions.\r\n\r\nRefunds on accommodation are only given in extenuating circumstances and are at the discretion of management.\r\nOur friendly staff is eager to welcome you! Get ready to make new friends, enjoy your stay, and have an unforgettable experience. If you have any questions, feel free to reach out—we’re happy to help!","hostelworldSays":null,"hostelSays":null,"location":{"address1":"40 Peninsular Drive","address2":"","city":{"id":645,"name":"Gold Coast","nameEN":"Gold Coast"},"country":{"id":13,"name":"Australia","nameEN":"Australia"},"region":{"id":76,"name":"Queensland","nameEN":"Queensland"},"latitude":"-28.0037463","longitude":"153.4244086","distance":{"kilometers":0.46,"miles":0.28}},"maxGuestsPerBooking":10,"depositPercentage":15,"ratings":{"security":69,"location":83,"staff":76,"atmosphere":61,"clean":52,"facilities":55,"value":57,"overall":65,"ratingsCount":1789},"groupInformation":{"listingInfo":"","terms":"We do not accept schoolies.","cancellationTerms":"","additionalTerms":"All groups must confirm with hostel before booking.","typesNotAccepted":["JUNIORPRIMARYSCHOOL","HIGHSECONDARYSCHOOL"],"remainderDue":"ON4WEEKS","ageRangesAccepted":["18-21","21-35","35-50"],"maxGuestsPerBooking":30},"currency":"AUD","houseRules":{"notes":"You must have an INTERNATIONAL passport and be between the ages of 18 - 35 years old to check-in in shared rooms.\r\n\r\nBackpackers in Paradise do not accept Schoolies.\r\n\r\nCancellations must be made at least 72 hours, prior to day of arrival.\r\n\r\nPlease be advised that we do not conduct check ins or check outs on Christmas Day and New Years Day.\r\n\r\nIf travelling as a couple or in a group, the resort does not guarantee that all beds will be in the same room. Guests who wish to stay in the same room are urged to book Private Backpacker Rooms.\r\n\r\nBackpackers In Paradise is a licensed premise and in accordance with the Liquor Act 1992 it is not permitted to bring alcohol onsite other than that is purchased through our bar.\r\nCancellation policy: 72h before arrival. In case of a late cancellation or No Show, you will be charged the first night of your stay.","checkin":{"from":14,"until":23},"latestCheckout":"10:00","policies":["TAXESINCLUDED"],"cancellationPolicy":{"canxDays":3,"freeCancellationEnabled":true}},"taxes":[],"hoscars":{"awards":[],"nominations":[]},"facilities":[{"name":"FACILITYCATEGORYFREE","id":1,"facilities":[{"id":30,"name":"FREEPARKING"},{"id":90,"name":"FREEWIFI"},{"id":103,"name":"FREEINTERNETACCESS"}]},{"name":"FACILITYCATEGORYGENERAL","id":2,"facilities":[{"id":28,"name":"BICYCLEPARKING"},{"id":113,"name":"JOBSBOARD"}]},{"name":"FACILITYCATEGORYSERVICES","id":3,"facilities":[{"id":15,"name":"LUGGAGESTORAGE"},{"id":21,"name":"TOURSTRAVELDESK"},{"id":77,"name":"ATM"},{"id":97,"name":"SHUTTLEBUS"},{"id":116,"name":"PARKING"},{"id":121,"name":"HOUSEKEEPING"},{"id":153,"name":"RECEPTIONLIMITEDHOURS"}]},{"name":"FACILITYCATEGORYENTERTAINMENT","id":5,"facilities":[{"id":4,"name":"INTERNETACCESS"},{"id":79,"name":"BOOKEXCHANGE"},{"id":84,"name":"PLAYSTATION"},{"id":95,"name":"BOARDGAMES"},{"id":106,"name":"CABLETV"},{"id":109,"name":"POOLTABLE"},{"id":133,"name":"WIFI"},{"id":384,"name":"GAMINGCONSOLES"},{"id":386,"name":"SMARTTV"}]},{"name":"FACILITYCATEGORYFOODANDDRINKS","id":4,"facilities":[{"id":12,"name":"BAR"},{"id":29,"name":"BBQ"},{"id":86,"name":"VENDINGMACHINES"},{"id":117,"name":"CAFE"},{"id":357,"name":"FILTEREDWATERDISPENSER"}]},{"name":"FACILITYCATEGORYKITCHEN","id":6,"facilities":[{"id":92,"name":"KITCHEN"}]},{"name":"FACILITYCATEGORYLAUNDRY","id":8,"facilities":[{"id":5,"name":"LAUNDRYFACILITIES"},{"id":102,"name":"DRYER"},{"id":122,"name":"IRONIRONINGBOARD"},{"id":131,"name":"WASHINGMACHINE"},{"id":368,"name":"FREEIRONIRONINGBOARD"},{"id":369,"name":"RECYCLINGBINS"}]},{"name":"FACILITYCATEGORYWELLNESS","id":9,"facilities":[{"id":16,"name":"SWIMMINGPOOL"},{"id":81,"name":"HOTSHOWERS"},{"id":118,"name":"OUTDOORSWIMMINGPOOL"}]},{"name":"FACILITYCATEGORYOUTDOORS","id":10,"facilities":[{"id":107,"name":"OUTDOORTERRACE"}]},{"name":"FACILITYCATEGORYSAFETYANDSECURITY","id":11,"facilities":[{"id":14,"name":"LOCKERS"},{"id":22,"name":"KEYCARDACCESS"},{"id":112,"name":"24HOURSECURITY"},{"id":376,"name":"FIREEXTINGUISHERS"},{"id":377,"name":"FIRSTAIDKITS"},{"id":378,"name":"SMOKEALARMS"}]},{"name":"FACILITYCATEGORYSOCIALAREAS","id":12,"facilities":[{"id":24,"name":"COMMONROOM"},{"id":108,"name":"GAMESROOM"},{"id":380,"name":"LOUNGEROOM"},{"id":381,"name":"SOCIALBALCONY"}]},{"name":"FACILITYCATEGORYBEDROOM","id":13,"facilities":[{"id":9,"name":"LINENINCLUDED"},{"id":50,"name":"AIRCONDITIONING"},{"id":119,"name":"HAIRDRYERS"},{"id":120,"name":"CEILINGFAN"}]},{"name":"FACILITYCATEGORYHOSTELWORLDPOLICIES","id":14,"facilities":[{"id":300,"name":"FLEXIBLENRR"}]},{"name":"FACILITYCATEGORYAVAILABLEFORAFEE","id":15,"facilities":[{"id":7,"name":"BICYCLEHIRE"},{"id":13,"name":"TOWELSFORHIRE"}]}],"images":[{"prefix":"a.hwstatic.com/image/upload/f_auto,q_auto","suffix":"/v1/propertyimages/2/2763/5024.jpg","position":1},{"prefix":"a.hwstatic.com/image/upload/f_auto,q_auto","suffix":"/v1/propertyimages/2/2763/wangsnlyocs2zipzdeqw","position":2},{"prefix":"a.hwstatic.com/image/upload/f_auto,q_auto","suffix":"/v1/propertyimages/2/2763/cosur3epo94gek0krjnv","position":3},{"prefix":"a.hwstatic.com/image/upload/f_auto,q_auto","suffix":"/v1/propertyimages/2/2763/g5rrblqzvlvxhunnrtfv","position":4},{"prefix":"a.hwstatic.com/image/upload/f_auto,q_auto","suffix":"/v1/propertyimages/2/2763/16.jpg","position":5},{"prefix":"a.hwstatic.com/image/upload/f_auto,q_auto","suffix":"/v1/propertyimages/2/2763/15.jpg","position":6},{"prefix":"a.hwstatic.com/image/upload/f_auto,q_auto","suffix":"/v1/propertyimages/2/2763/13.jpg","position":7},{"prefix":"a.hwstatic.com/image/upload/f_auto,q_auto","suffix":"/v1/propertyimages/2/2763/ndzj8332uhrjpasabk0v","position":8},{"prefix":"a.hwstatic.com/image/upload/f_auto,q_auto","suffix":"/v1/propertyimages/2/2763/iyjyzvae43ztmknba52g","position":9},{"prefix":"a.hwstatic.com/image/upload/f_auto,q_auto","suffix":"/v1/propertyimages/2/2763/509.jpg","position":10},{"prefix":"a.hwstatic.com/image/upload/f_auto,q_auto","suffix":"/v1/propertyimages/2/2763/8.jpg","position":11},{"prefix":"a.hwstatic.com/image/upload/f_auto,q_auto","suffix":"/v1/propertyimages/2/2763/14.jpg","position":12},{"prefix":"a.hwstatic.com/image/upload/f_auto,q_auto","suffix":"/v1/propertyimages/2/2763/xeunmnebdznapjpquprf","position":13},{"prefix":"a.hwstatic.com/image/upload/f_auto,q_auto","suffix":"/v1/propertyimages/2/2763/18.jpg","position":14},{"prefix":"a.hwstatic.com/image/upload/f_auto,q_auto","suffix":"/v1/propertyimages/2/2763/502.jpg","position":15},{"prefix":"a.hwstatic.com/image/upload/f_auto,q_auto","suffix":"/v1/propertyimages/2/2763/ovc8yj3vhfmiiisekqnv","position":16},{"prefix":"a.hwstatic.com/image/upload/f_auto,q_auto","suffix":"/v1/propertyimages/2/2763/cxumacvisjfmaousttfr","position":17},{"prefix":"a.hwstatic.com/image/upload/f_auto,q_auto","suffix":"/v1/propertyimages/2/2763/k8meo8vm9o484vwxgpuv","position":18},{"prefix":"a.hwstatic.com/image/upload/f_auto,q_auto","suffix":"/v1/propertyimages/2/2763/504.jpg","position":19},{"prefix":"a.hwstatic.com/image/upload/f_auto,q_auto","suffix":"/v1/propertyimages/2/2763/yzshvprrgq3kzyh1rybd","position":20},{"prefix":"a.hwstatic.com/image/upload/f_auto,q_auto","suffix":"/v1/propertyimages/2/2763/z6tqlp0k5zn4dplf6igz","position":21},{"prefix":"a.hwstatic.com/image/upload/f_auto,q_auto","suffix":"/v1/propertyimages/2/2763/pjmdrizmr3gxtb5ph4rj","position":22},{"prefix":"a.hwstatic.com/image/upload/f_auto,q_auto","suffix":"/v1/propertyimages/2/2763/507.jpg","position":23},{"prefix":"a.hwstatic.com/image/upload/f_auto,q_auto","suffix":"/v1/propertyimages/2/2763/jaesaxbmgugnfa4a9yqo","position":24},{"prefix":"a.hwstatic.com/image/upload/f_auto,q_auto","suffix":"/v1/propertyimages/2/2763/5010.jpg","position":25}],"videos":[{"id":99495,"url":"https://www.youtube.com/embed/ltnDJIr2NZ4","still":"https://img.youtube.com/vi/ltnDJIr2NZ4/0.jpg"}],"video":"https://www.youtube.com/embed/ltnDJIr2NZ4","payments":{"payNow":false},"paymentMethods":["Visa","Mastercard","VisaDebit","Electron","Maestro","JCB"],"hostelworldRecommends":false,"isElevateProperty":false,"hasExperiences":false,"timesBookedToday":7,"promotions":[{"id":241559,"type":"CUSTOM","stack":false,"name":"ALLPLATFORMS","created":"2025-09-17T06:44:33","isActive":true,"conditions":{"stayDates":{"isTotalNightsGreaterOrEqualThan":1,"isDayOfWeekOneOf":["Monday","Tuesday","Wednesday","Thursday","Sunday"]},"propertyIds":{"containsAnyOf":[2763]},"ratePlanTypes":{"containsAnyStringOf":["Standard","NRR","Standard_BB","NRR_BB"]},"roomTypeIds":{"containsAnyOf":[14518,14519,473965,320254,423497,483264,816808,951858]}},"benefits":{"PERCENTDISCOUNT":{"value":16}}},{"id":241558,"type":"CUSTOM","stack":false,"name":"Autumn Deals","created":"2025-09-17T06:40:36","isActive":true,"conditions":{"stayDates":{"isAfterOrSameDayThan":"2025-10-01","isBeforeOrSameDayThan":"2025-11-30","isNotOneDayOf":["2025-10-03","2025-10-04","2025-10-10","2025-10-11","2025-10-17","2025-10-18","2025-10-24","2025-10-25","2025-10-31","2025-11-01","2025-11-07","2025-11-08","2025-11-14","2025-11-15","2025-11-21","2025-11-22","2025-11-28","2025-11-29"],"isTotalNightsGreaterOrEqualThan":1},"propertyIds":{"containsAnyOf":[2763]},"ratePlanTypes":{"containsAnyStringOf":["Standard","NRR","Standard_BB","NRR_BB"]}},"benefits":{"PERCENTDISCOUNT":{"value":5}},"campaign":{"id":"t6X1wsBWAmCSrqEXT43t","name":"Autumn Deals","start":"2025-09-18T00:00:00Z","end":"2025-10-27T23:59:00Z"}}],"categories":[]}
